README.md
setup.cfg
setup.py
Chrome_Cut.egg-info/PKG-INFO
Chrome_Cut.egg-info/SOURCES.txt
Chrome_Cut.egg-info/dependency_links.txt
Chrome_Cut.egg-info/entry_points.txt
Chrome_Cut.egg-info/not-zip-safe
Chrome_Cut.egg-info/requires.txt
Chrome_Cut.egg-info/top_level.txt
chrome_cut/__init__.py
chrome_cut/core.py
chrome_cut/fix3.py