Metadata-Version: 1.1
Name: Chrome-Cut
Version: 0.2.2
Summary: Command line tool to scan and control chrome cast devices.
Home-page: https://github.com/mrf345/chrome-cut-cli/
Author: Mohamed Feddad
Author-email: mrf345@gmail.com
License: MPL 2.0
Download-URL: https://github.com/mrf345/chrome-cut-cli/archive/0.2.2.tar.gz
Keywords: chrome,cast,chromecast,control,monitor,restore,stream,scan
Platform: any
Classifier: Development Status :: 4 - Beta
Classifier: Environment :: Console
Classifier: Intended Audience :: End Users/Desktop
Classifier: Intended Audience :: System Administrators
Classifier: License :: OSI Approved :: Mozilla Public License 2.0 (MPL 2.0)
Classifier: Natural Language :: English
Classifier: Operating System :: OS Independent
Classifier: Programming Language :: Python
Classifier: Topic :: Security
Classifier: Topic :: System :: Monitoring
Classifier: Topic :: Utilities
